noloadj/__init__.py
noloadj/ODE/ode44.py
noloadj/ODE/ode45.py
noloadj/ODE/ode45_extract.py
noloadj/ODE/ode45_extract_fft.py
noloadj/ODE/ode45_fft.py
noloadj/ODE/ode_tools.py
noloadj/analyse/DGSM.py
noloadj/analyse/Sobol.py
noloadj/analyse/simulation.py
noloadj/gui/OpenGUI.py
noloadj/gui/gui1.py
noloadj/gui/plotIterations.py
noloadj/gui/plotPareto.py
noloadj/gui/testOverLabels.py
noloadj/numerical_methods/__init__.py
noloadj/numerical_methods/ODE/__init__.py
noloadj/numerical_methods/ODE/ode44.py
noloadj/numerical_methods/ODE/ode45.py
noloadj/numerical_methods/ODE/ode45_extract.py
noloadj/numerical_methods/ODE/ode_extracted_features.py
noloadj/numerical_methods/ODE/ode_tools.py
noloadj/numerical_methods/interpolation/__init__.py
noloadj/numerical_methods/interpolation/interpolate1D.py
noloadj/numerical_methods/interpolation/interpolate2D.py
noloadj/optimization/ExportToXML.py
noloadj/optimization/Tools.py
noloadj/optimization/__init__.py
noloadj/optimization/iterationHandler.py
noloadj/optimization/multiobjective.py
noloadj/optimization/optimProblem.py
noloadj/optimization/paretoTools.py
noloadj/optimization/specifications.py
noloadj/optimization/wrapper.py
noloadj/tutorial/01-UnconstrainedMonoObjective.py
noloadj/tutorial/02-ConstrainedMonoObjective.py
noloadj/tutorial/03-ConstrainedMultiObjective.py
noloadj/tutorial/04-ConstrainedMonoObjective2.py
noloadj/tutorial/05-SensitivityAnalysis.py
noloadj/tutorial/05_SensitivityAnalysis.py
noloadj/tutorial/plotTools.py
noloadj-1.4.0.dist-info/AUTHORS.md
noloadj-1.4.0.dist-info/LICENSE
noloadj-1.4.0.dist-info/METADATA
noloadj-1.4.0.dist-info/WHEEL
noloadj-1.4.0.dist-info/top_level.txt
noloadj-1.4.0.dist-info/RECORD
