Metadata-Version: 2.1
Name: noloadj
Version: 1.4.0
Summary: solving constrained optimization problem for the design of engineering systems
Home-page: UNKNOWN
Author: B. DELINCHANT, L. GERBAUD, F. WURTZ, L.AGOBERT
Author-email: benoit.delinchant@G2ELab.grenoble-inp.fr
License: UNKNOWN
Platform: UNKNOWN
Classifier: Programming Language :: Python
Classifier: License :: OSI Approved :: Apache Software License
Classifier: Programming Language :: Python :: 3.10
Classifier: Topic :: Scientific/Engineering
License-File: LICENSE
License-File: AUTHORS.md
Requires-Dist: Matplotlib (>3.0)
Requires-Dist: Scipy (>=1.2)
Requires-Dist: Jax (>=0.4.18)
Requires-Dist: Jaxlib (>=0.4.18)
Requires-Dist: Pandas (>=1.3.5)
Requires-Dist: tk (>=0.1.0)
Requires-Dist: Openpyxl (>=3.1.2)
